at_serial_can/__init__.py
at_serial_can/at_serial_can.py
at_serial_can-1.0.4.dist-info/LICENSE
at_serial_can-1.0.4.dist-info/METADATA
at_serial_can-1.0.4.dist-info/WHEEL
at_serial_can-1.0.4.dist-info/top_level.txt
at_serial_can-1.0.4.dist-info/RECORD
