Metadata-Version: 2.1
Name: at-serial-can
Version: 1.0.4
Summary: AT Command Style Serial to CAN interface modules
Home-page: https://github.com/gueei/at_serial_can
Author: Andy Tsui
Author-email: gueei.com@gmail.com
License: UNKNOWN
Project-URL: Bug Tracker, https://github.com/gueei/at_serial_can/issues
Platform: UNKNOWN
Classifier: Programming Language :: Python :: 3
Classifier: License :: OSI Approved :: MIT License
Classifier: Operating System :: OS Independent
Requires-Python: >=3.6
License-File: LICENSE
